unipercept/__init__.py
unipercept/_api_config.py
unipercept/_api_data.py
unipercept/_monkeypatch.py
unipercept/config.py
unipercept/file_io.py
unipercept/log.py
unipercept/model.py
unipercept/py.typed
unipercept/state.py
unipercept/api/__init__.py
unipercept/cli/__init__.py
unipercept/cli/__main__.py
unipercept/cli/_command.py
unipercept/cli/_config.py
unipercept/cli/_utils.py
unipercept/cli/backbones.py
unipercept/cli/datasets.py
unipercept/cli/echo.py
unipercept/cli/evaluate.py
unipercept/cli/profile.py
unipercept/cli/trace.py
unipercept/cli/train.py
unipercept/data/__init__.py
unipercept/data/_helpers.py
unipercept/data/_loader.py
unipercept/data/collect.py
unipercept/data/ops.py
unipercept/data/pseudolabeler.py
unipercept/data/tokenizer.py
unipercept/data/io/__init__.py
unipercept/data/io/_camera.py
unipercept/data/io/_read.py
unipercept/data/pipes/__init__.py
unipercept/data/pipes/_cache.py
unipercept/data/pipes/_io_wrap.py
unipercept/data/pipes/_join.py
unipercept/data/pipes/_pattern.py
unipercept/data/pipes/_pil.py
unipercept/data/sets/__init__.py
unipercept/data/sets/_base.py
unipercept/data/sets/_generic.py
unipercept/data/sets/cityscapes.py
unipercept/data/sets/huggingface.py
unipercept/data/sets/kitti_360.py
unipercept/data/sets/kitti_sem.py
unipercept/data/sets/kitti_step.py
unipercept/data/sets/pascal_voc.py
unipercept/data/sets/vistas.py
unipercept/data/sets/wilddash.py
unipercept/data/tensors/__init__.py
unipercept/data/tensors/_depth.py
unipercept/data/tensors/_flow.py
unipercept/data/tensors/_panoptic.py
unipercept/data/tensors/_torchvision.py
unipercept/data/tensors/helpers.py
unipercept/data/tensors/registry.py
unipercept/data/types/__init__.py
unipercept/data/types/_coco.py
unipercept/data/types/_info.py
unipercept/data/types/_manifest.py
unipercept/data/types/sanity.py
unipercept/engine/__init__.py
unipercept/engine/_engine.py
unipercept/engine/_optimizer.py
unipercept/engine/_params.py
unipercept/engine/_scheduler.py
unipercept-5.1.3.dist-info/LICENSE
unipercept-5.1.3.dist-info/METADATA
unipercept-5.1.3.dist-info/WHEEL
unipercept-5.1.3.dist-info/entry_points.txt
unipercept-5.1.3.dist-info/top_level.txt
unipercept-5.1.3.dist-info/RECORD
