Metadata-Version: 2.1
Name: unipercept
Version: 5.1.3
Summary: UniPecept: A unified framework for perception tasks focusing on research applications that require a high degree of flexibility and customization.
Author-email: Kurt Stolle <k.h.w.stolle@gmail.com>
Keywords: perception,computer vision,deep learning,object detection,instance segmentation,semantic segmentation
Classifier: Development Status :: 4 - Beta
Classifier: Programming Language :: Python
Classifier: Programming Language :: Python :: 3.11
Classifier: Programming Language :: Python :: Implementation :: CPython
Requires-Python: >=3.11
License-File: LICENSE
Requires-Dist: tensordict >=0.3.0
Requires-Dist: einops >=0.7.0
Requires-Dist: timm >=0.6.14
Requires-Dist: bullet >=2.2.0
Requires-Dist: accelerate >=0.27.0
Requires-Dist: statistics
Requires-Dist: h5py
Requires-Dist: opencv-python
Requires-Dist: omegaconf
Requires-Dist: hydra-core
Requires-Dist: unitrack
Requires-Dist: iopath
Requires-Dist: torchdata
Requires-Dist: fvcore
Requires-Dist: transformers
Requires-Dist: seaborn
Requires-Dist: matplotlib
Requires-Dist: tabulate
Requires-Dist: termcolor
Requires-Dist: pycocotools
Requires-Dist: ftfy
Provides-Extra: docs
Requires-Dist: sphinx ; extra == 'docs'
Requires-Dist: sphinx-rtd-theme ; extra == 'docs'
Requires-Dist: numpydoc ; extra == 'docs'
Provides-Extra: notebooks
Requires-Dist: jupyterlab ; extra == 'notebooks'
Requires-Dist: ipywidgets ; extra == 'notebooks'
Requires-Dist: ipykernel ; extra == 'notebooks'
Requires-Dist: ipython-autotime ; extra == 'notebooks'
Requires-Dist: matplotlib ; extra == 'notebooks'
Requires-Dist: seaborn ; extra == 'notebooks'
Provides-Extra: tests
Requires-Dist: hypothesis ; extra == 'tests'
Requires-Dist: bandit[toml] ; extra == 'tests'
Requires-Dist: black >=23.10.0 ; extra == 'tests'
Requires-Dist: check-manifest ; extra == 'tests'
Requires-Dist: flake8 ; extra == 'tests'
Requires-Dist: flake8-bugbear ; extra == 'tests'
Requires-Dist: flake8-docstrings ; extra == 'tests'
Requires-Dist: flake8-formatter-junit-xml ; extra == 'tests'
Requires-Dist: flake8-import-conventions ; extra == 'tests'
Requires-Dist: flake8-unused-arguments ; extra == 'tests'
Requires-Dist: flake8-comprehensions ; extra == 'tests'
Requires-Dist: flake8-errmsg ; extra == 'tests'
Requires-Dist: flake8-logging-format ; extra == 'tests'
Requires-Dist: flake8-pie ; extra == 'tests'
Requires-Dist: flake8-pyi ; extra == 'tests'
Requires-Dist: flake8-pytest-style ; extra == 'tests'
Requires-Dist: flake8-return ; extra == 'tests'
Requires-Dist: flake8-2020 ; extra == 'tests'
Requires-Dist: flake8-executable ; extra == 'tests'
Requires-Dist: flake8-simplify ; extra == 'tests'
Requires-Dist: flake8-black ; extra == 'tests'
Requires-Dist: flake8-pyproject ; extra == 'tests'
Requires-Dist: pre-commit ; extra == 'tests'
Requires-Dist: pygrep ; extra == 'tests'
Requires-Dist: isort ; extra == 'tests'
Requires-Dist: pandas-vet ; extra == 'tests'
Requires-Dist: refurb ; extra == 'tests'
Requires-Dist: pylint ; extra == 'tests'
Requires-Dist: pylint-junit ; extra == 'tests'
Requires-Dist: pytest ; extra == 'tests'
Requires-Dist: pytest-sugar ; extra == 'tests'
Requires-Dist: pytest-xdist ; extra == 'tests'
Requires-Dist: pytest-benchmark ; extra == 'tests'
Requires-Dist: pytest-cov ; extra == 'tests'
Requires-Dist: pytest-mock ; extra == 'tests'
Requires-Dist: pytest-runner ; extra == 'tests'
Requires-Dist: pytest-github-actions-annotate-failures ; extra == 'tests'
Requires-Dist: shellcheck-py ; extra == 'tests'
Requires-Dist: mypy ; extra == 'tests'
Requires-Dist: autoflake ; extra == 'tests'
Requires-Dist: pydocstyle ; extra == 'tests'
Requires-Dist: pyre-check ; extra == 'tests'
Requires-Dist: pydocstringformatter ; extra == 'tests'
Requires-Dist: pyrefact ; extra == 'tests'
Requires-Dist: pyflakes ; extra == 'tests'
Requires-Dist: mccabe ; extra == 'tests'
